{"slicevar_max":7.39885,"sfnr_data_json":"qa_sfnrdata_fmriSeriesEncode_1Run3_7.bxh.raw.jpg.json","slicevar_cbar_json":"qa_slicevarcbar.raw.jpg.json","slicevar_data_json":"qa_slicevardata_fmriSeriesEncode_1Run3_7.bxh.png.json","stddev_cbar_json":"qa_stddevcbar.raw.jpg.json","slicevar_scaled_min":"0.00027157","sfnr_max":126.101,"mean_min":0,"mean_cbar_json":"qa_meancbar.raw.jpg.json","stddev_scaled_max":"332.667","sfnr_scaled_max":"126.101","stddev_scaled_min":"0","slicevar_data":"qa_slicevardata_fmriSeriesEncode_1Run3_7.bxh.png","mask_min":0,"stddev_data_json":"qa_stddevdata_fmriSeriesEncode_1Run3_7.bxh.raw.jpg.json","mask_scaled_min":"0","mask_max":1,"sfnr_min":0,"mean_data_json":"qa_meandata_fmriSeriesEncode_1Run3_7.bxh.raw.jpg.json","stddev_max":332.667,"slicevar_min":0.00027157,"mask_scaled_max":"1","sfnr_scaled_min":"0","mean_max":1943.12,"stddev_min":0,"mask_data":"qa_maskdata_fmriSeriesEncode_1Run3_7.bxh.png","mean_scaled_max":"1943.12","sfnr_cbar_json":"qa_sfnrcbar.raw.jpg.json","slicevar_scaled_max":"7.39885","mean_scaled_min":"0"}